{
  "name":"client-app-add-routed-element-tabs",
  "version":"1.0.0",
  "component": true,
  "description":"Tabs of routed, page elements",
  "author":"Tony Mobily",
  "moduleDependencies":[
    "client-app-frame"
  ],
  "manipulate":{
    "text":{
      "<%=userInput['client-app-add-routed-element-tabs'].destination.file%>":[
        {
           "op":"insert",
           "position":"after",
           "newlineAfter":true,
           "anchorPoint":"<!-- Element insertion point -->",
           "valueFromFile":"routed-element-tabs.js"
        }
      ]
    }
  },
  "position": -1,
}
